Metadata-Version: 1.0
Name: shubhmcoeprob
Version: 0.6
Summary: Gaussian and Binomial distributions
Home-page: UNKNOWN
Author: shubhmcoe
Author-email: shubhmcoe@gmail.com
License: UNKNOWN
Platform: UNKNOWN
